vgg_named/__init__.py
vgg_named/sequential_extractor.py
vgg_named/vgg_named.py
pytorch_vgg_named-0.3.dist-info/LICENSE
pytorch_vgg_named-0.3.dist-info/METADATA
pytorch_vgg_named-0.3.dist-info/WHEEL
pytorch_vgg_named-0.3.dist-info/top_level.txt
pytorch_vgg_named-0.3.dist-info/RECORD
