Metadata-Version: 2.1
Name: pytorch-vgg-named
Version: 0.3
Summary: Named VGG feature extraction
Home-page: http://github.com/black-puppydog/pytorch_vgg_named
Author: Daan Wynen
Author-email: daan.wynen@inria.fr
License: UNKNOWN
Platform: UNKNOWN
Classifier: Programming Language :: Python :: 3
Classifier: License :: OSI Approved :: BSD License
Classifier: Operating System :: OS Independent
Requires-Python: >=3.6
Requires-Dist: torch (>=1.0)
Requires-Dist: torchvision (>=0.2)
